podsearch_ai/.DS_Store
podsearch_ai/__init__.py
podsearch_ai/searcher.py
podsearch_ai-0.2.0.dist-info/WHEEL
podsearch_ai-0.2.0.dist-info/METADATA
podsearch_ai-0.2.0.dist-info/RECORD
