Metadata-Version: 2.1
Name: podsearch_ai
Version: 0.2.0
Summary: Let's find some podcasts!
Home-page: https://github.com/hangligit/podsearch_ai-py
Author: Hang Li
Author-email: bitlihang@gmail.com
Requires-Python: >=3.7
Classifier: License :: OSI Approved :: MIT License
